{"tables":[{"table_name":"customers","columns":[{"col_name":"customer_id","type":"varchar"},{"col_name":"first_name","type":"varchar"},{"col_name":"first_order","type":"varchar"},{"col_name":"last_name","type":"varchar"},{"col_name":"most_recent_order","type":"varchar"},{"col_name":"number_of_orders","type":"varchar"}]},{"table_name":"stg_orders","columns":[{"col_name":"customer_id","type":"varchar"},{"col_name":"order_date","type":"varchar"},{"col_name":"order_id","type":"varchar"},{"col_name":"status","type":"varchar"}]},{"table_name":"stg_customers","columns":[{"col_name":"customer_id","type":"varchar"},{"col_name":"first_name","type":"varchar"},{"col_name":"last_name","type":"varchar"}]},{"table_name":"orders","columns":[{"col_name":"amount","type":"varchar"},{"col_name":"bank_transfer_amount","type":"varchar"},{"col_name":"coupon_amount","type":"varchar"},{"col_name":"credit_card_amount","type":"varchar"},{"col_name":"customer_id","type":"varchar"},{"col_name":"gift_card_amount","type":"varchar"},{"col_name":"order_date","type":"varchar"},{"col_name":"order_id","type":"varchar"},{"col_name":"status","type":"varchar"},{"col_name":"deprecated_order_id","type":"varchar"}]},{"table_name":"stg_payments","columns":[{"col_name":"amount","type":"varchar"},{"col_name":"order_id","type":"varchar"},{"col_name":"payment_id","type":"varchar"},{"col_name":"payment_method","type":"varchar"}]},{"table_name":"raw_customers","columns":[{"col_name":"id","type":"varchar"},{"col_name":"first_name","type":"varchar"},{"col_name":"last_name","type":"varchar"}]},{"table_name":"raw_payments","columns":[{"col_name":"amount","type":"varchar"},{"col_name":"id","type":"varchar"},{"col_name":"order_id","type":"varchar"},{"col_name":"payment_method","type":"varchar"}]},{"table_name":"raw_orders","columns":[{"col_name":"id","type":"varchar"},{"col_name":"order_date","type":"varchar"},{"col_name":"status","type":"varchar"},{"col_name":"user_id","type":"varchar"}]}],"edges":[{"src_column":{"table_name":"stg_orders","col_name":"order_date"},"dst_column":{"table_name":"customers","col_name":"most_recent_order"},"confidence":1},{"src_column":{"table_name":"stg_orders","col_name":"order_date"},"dst_column":{"table_name":"customers","col_name":"first_order"},"confidence":1},{"src_column":{"table_name":"stg_orders","col_name":"order_id"},"dst_column":{"table_name":"customers","col_name":"number_of_orders"},"confidence":1},{"src_column":{"table_name":"stg_customers","col_name":"customer_id"},"dst_column":{"table_name":"customers","col_name":"customer_id"},"confidence":1},{"src_column":{"table_name":"stg_customers","col_name":"last_name"},"dst_column":{"table_name":"customers","col_name":"last_name"},"confidence":1},{"src_column":{"table_name":"stg_customers","col_name":"first_name"},"dst_column":{"table_name":"customers","col_name":"first_name"},"confidence":1},{"src_column":{"table_name":"stg_payments","col_name":"amount"},"dst_column":{"table_name":"orders","col_name":"gift_card_amount"},"confidence":1},{"src_column":{"table_name":"stg_payments","col_name":"amount"},"dst_column":{"table_name":"orders","col_name":"bank_transfer_amount"},"confidence":1},{"src_column":{"table_name":"stg_payments","col_name":"amount"},"dst_column":{"table_name":"orders","col_name":"amount"},"confidence":1},{"src_column":{"table_name":"stg_orders","col_name":"customer_id"},"dst_column":{"table_name":"orders","col_name":"customer_id"},"confidence":1},{"src_column":{"table_name":"stg_orders","col_name":"order_id"},"dst_column":{"table_name":"orders","col_name":"order_id"},"confidence":1},{"src_column":{"table_name":"stg_payments","col_name":"order_id"},"dst_column":{"table_name":"orders","col_name":"order_id"},"confidence":1},{"src_column":{"table_name":"stg_orders","col_name":"status"},"dst_column":{"table_name":"orders","col_name":"status"},"confidence":1},{"src_column":{"table_name":"stg_orders","col_name":"order_date"},"dst_column":{"table_name":"orders","col_name":"order_date"},"confidence":1},{"src_column":{"table_name":"stg_payments","col_name":"amount"},"dst_column":{"table_name":"orders","col_name":"coupon_amount"},"confidence":1},{"src_column":{"table_name":"stg_payments","col_name":"amount"},"dst_column":{"table_name":"orders","col_name":"credit_card_amount"},"confidence":1},{"src_column":{"table_name":"raw_customers","col_name":"last_name"},"dst_column":{"table_name":"stg_customers","col_name":"last_name"},"confidence":1},{"src_column":{"table_name":"raw_customers","col_name":"first_name"},"dst_column":{"table_name":"stg_customers","col_name":"first_name"},"confidence":1},{"src_column":{"table_name":"raw_customers","col_name":"id"},"dst_column":{"table_name":"stg_customers","col_name":"customer_id"},"confidence":1},{"src_column":{"table_name":"raw_payments","col_name":"amount"},"dst_column":{"table_name":"stg_payments","col_name":"amount"},"confidence":1},{"src_column":{"table_name":"raw_payments","col_name":"payment_method"},"dst_column":{"table_name":"stg_payments","col_name":"payment_method"},"confidence":1},{"src_column":{"table_name":"raw_payments","col_name":"order_id"},"dst_column":{"table_name":"stg_payments","col_name":"order_id"},"confidence":1},{"src_column":{"table_name":"raw_payments","col_name":"id"},"dst_column":{"table_name":"stg_payments","col_name":"payment_id"},"confidence":1},{"src_column":{"table_name":"raw_orders","col_name":"status"},"dst_column":{"table_name":"stg_orders","col_name":"status"},"confidence":1},{"src_column":{"table_name":"raw_orders","col_name":"order_date"},"dst_column":{"table_name":"stg_orders","col_name":"order_date"},"confidence":1},{"src_column":{"table_name":"raw_orders","col_name":"user_id"},"dst_column":{"table_name":"stg_orders","col_name":"customer_id"},"confidence":1},{"src_column":{"table_name":"raw_orders","col_name":"id"},"dst_column":{"table_name":"stg_orders","col_name":"order_id"},"confidence":1}]}